Workbook
Name data: OFFSET('0-1'!$A$1,0,0,周题库!$C$3,1)
Name data1: OFFSET('0-1'!$C$1,0,0,周题库!$H$3,1)
Name data2: OFFSET('0-1'!$E$1,0,0,日题库!$C$3,1)
Name data3: OFFSET('0-1'!$G$1,0,0,日题库!$H$3,1)

Sheet 周题库
B1: 旧单词起始点 | C1: =VLOOKUP(#REF!,词库!#REF!,2,0) -> #REF! | G1: 新单词起始点 | H1: =VLOOKUP(#REF!,词库!#REF!,2,0) -> #REF!
B2: 旧单词结束点 | C2: =VLOOKUP(#REF!,词库!#REF!,3,0) -> #REF! | G2: 新单词结束点 | H2: =VLOOKUP(#REF!,词库!#REF!,3,0) -> #REF!
B3: 测试步长 | C3: =C2-C1 -> #REF! | G3: 测试步长 | H3: =H2-H1 -> #REF!
B4: =$C$1+RANK('0-1'!A1,data) -> #REF! | C4: =VLOOKUP(B:B,词库!$A:$C,2,0) -> #REF! | D4: =VLOOKUP(B:B,词库!$A:$C,3,0) -> #REF! | G4: =$H$1+RANK('0-1'!C1,data1) -> #REF! | H4: =VLOOKUP(G:G,词库!$A:$C,2,0) -> #REF! | I4: =VLOOKUP(G:G,词库!$A:$C,3,0) -> #REF!
B5: =$C$1+RANK('0-1'!A2,data) -> #REF! | C5: =VLOOKUP(B:B,词库!$A:$C,2,0) -> #REF! | D5: =VLOOKUP(B:B,词库!$A:$C,3,0) -> #REF! | G5: =$H$1+RANK('0-1'!C2,data1) -> #REF! | H5: =VLOOKUP(G:G,词库!$A:$C,2,0) -> #REF! | I5: =VLOOKUP(G:G,词库!$A:$C,3,0) -> #REF!
B6: =$C$1+RANK('0-1'!A3,data) -> #REF! | C6: =VLOOKUP(B:B,词库!$A:$C,2,0) -> #REF! | D6: =VLOOKUP(B:B,词库!$A:$C,3,0) -> #REF! | G6: =$H$1+RANK('0-1'!C3,data1) -> #REF! | H6: =VLOOKUP(G:G,词库!$A:$C,2,0) -> #REF! | I6: =VLOOKUP(G:G,词库!$A:$C,3,0) -> #REF!
B7: =$C$1+RANK('0-1'!A4,data) -> #REF! | C7: =VLOOKUP(B:B,词库!$A:$C,2,0) -> #REF! | D7: =VLOOKUP(B:B,词库!$A:$C,3,0) -> #REF! | G7: =$H$1+RANK('0-1'!C4,data1) -> #REF! | H7: =VLOOKUP(G:G,词库!$A:$C,2,0) -> #REF! | I7: =VLOOKUP(G:G,词库!$A:$C,3,0) -> #REF!
B8: =$C$1+RANK('0-1'!A5,data) -> #REF! | C8: =VLOOKUP(B:B,词库!$A:$C,2,0) -> #REF! | D8: =VLOOKUP(B:B,词库!$A:$C,3,0) -> #REF! | G8: =$H$1+RANK('0-1'!C5,data1) -> #REF! | H8: =VLOOKUP(G:G,词库!$A:$C,2,0) -> #REF! | I8: =VLOOKUP(G:G,词库!$A:$C,3,0) -> #REF!
B9: =$C$1+RANK('0-1'!A6,data) -> #REF! | C9: =VLOOKUP(B:B,词库!$A:$C,2,0) -> #REF! | D9: =VLOOKUP(B:B,词库!$A:$C,3,0) -> #REF! | G9: =$H$1+RANK('0-1'!C6,data1) -> #REF! | H9: =VLOOKUP(G:G,词库!$A:$C,2,0) -> #REF! | I9: =VLOOKUP(G:G,词库!$A:$C,3,0) -> #REF!
B10: =$C$1+RANK('0-1'!A7,data) -> #REF! | C10: =VLOOKUP(B:B,词库!$A:$C,2,0) -> #REF! | D10: =VLOOKUP(B:B,词库!$A:$C,3,0) -> #REF! | G10: =$H$1+RANK('0-1'!C7,data1) -> #REF! | H10: =VLOOKUP(G:G,词库!$A:$C,2,0) -> #REF! | I10: =VLOOKUP(G:G,词库!$A:$C,3,0) -> #REF!
B11: =$C$1+RANK('0-1'!A8,data) -> #REF! | C11: =VLOOKUP(B:B,词库!$A:$C,2,0) -> #REF! | D11: =VLOOKUP(B:B,词库!$A:$C,3,0) -> #REF! | G11: =$H$1+RANK('0-1'!C8,data1) -> #REF! | H11: =VLOOKUP(G:G,词库!$A:$C,2,0) -> #REF! | I11: =VLOOKUP(G:G,词库!$A:$C,3,0) -> #REF!
B12: =$C$1+RANK('0-1'!A9,data) -> #REF! | C12: =VLOOKUP(B:B,词库!$A:$C,2,0) -> #REF! | D12: =VLOOKUP(B:B,词库!$A:$C,3,0) -> #REF! | G12: =$H$1+RANK('0-1'!C9,data1) -> #REF! | H12: =VLOOKUP(G:G,词库!$A:$C,2,0) -> #REF! | I12: =VLOOKUP(G:G,词库!$A:$C,3,0) -> #REF!
B13: =$C$1+RANK('0-1'!A10,data) -> #REF! | C13: =VLOOKUP(B:B,词库!$A:$C,2,0) -> #REF! | D13: =VLOOKUP(B:B,词库!$A:$C,3,0) -> #REF! | G13: =$H$1+RANK('0-1'!C10,data1) -> #REF! | H13: =VLOOKUP(G:G,词库!$A:$C,2,0) -> #REF! | I13: =VLOOKUP(G:G,词库!$A:$C,3,0) -> #REF!
B14: =$C$1+RANK('0-1'!A11,data) -> #REF! | C14: =VLOOKUP(B:B,词库!$A:$C,2,0) -> #REF! | D14: =VLOOKUP(B:B,词库!$A:$C,3,0) -> #REF! | G14: =$H$1+RANK('0-1'!C11,data1) -> #REF! | H14: =VLOOKUP(G:G,词库!$A:$C,2,0) -> #REF! | I14: =VLOOKUP(G:G,词库!$A:$C,3,0) -> #REF!
B15: =$C$1+RANK('0-1'!A12,data) -> #REF! | C15: =VLOOKUP(B:B,词库!$A:$C,2,0) -> #REF! | D15: =VLOOKUP(B:B,词库!$A:$C,3,0) -> #REF! | G15: =$H$1+RANK('0-1'!C12,data1) -> #REF! | H15: =VLOOKUP(G:G,词库!$A:$C,2,0) -> #REF! | I15: =VLOOKUP(G:G,词库!$A:$C,3,0) -> #REF!
... B73: =$C$1+RANK('0-1'!A70,data) -> #REF! | C73: =VLOOKUP(B:B,词库!$A:$C,2,0) -> #REF! | D73: =VLOOKUP(B:B,词库!$A:$C,3,0) -> #REF! | G73: =$H$1+RANK('0-1'!C70,data1) -> #REF! | H73: =VLOOKUP(G:G,词库!$A:$C,2,0) -> #REF! | I73: =VLOOKUP(G:G,词库!$A:$C,3,0) -> #REF!

Sheet 日题库
B1: 旧单词起始点 | C1: =VLOOKUP(#REF!,词库!#REF!,2,0) -> #REF! | G1: 新单词起始点 | H1: =VLOOKUP(#REF!,词库!#REF!,2,0) -> #REF!
B2: 旧单词结束点 | C2: =VLOOKUP(#REF!,词库!#REF!,3,0) -> #REF! | G2: 新单词结束点 | H2: =VLOOKUP(#REF!,词库!#REF!,3,0) -> #REF!
B3: 测试步长 | C3: =C2-C1 -> #REF! | G3: 测试步长 | H3: =H2-H1 -> #REF!
B4: =$C$1+RANK('0-1'!E1,data2) -> #REF! | C4: =VLOOKUP(B:B,词库!$A:$C,2,0) -> #REF! | D4: =VLOOKUP(B:B,词库!$A:$C,3,0) -> #REF! | G4: =$H$1+RANK('0-1'!G1,data3) -> #REF! | H4: =VLOOKUP(G:G,词库!$A:$C,2,0) -> #REF! | I4: =VLOOKUP(G:G,词库!$A:$C,3,0) -> #REF!
B5: =$C$1+RANK('0-1'!E2,data2) -> #REF! | C5: =VLOOKUP(B:B,词库!$A:$C,2,0) -> #REF! | D5: =VLOOKUP(B:B,词库!$A:$C,3,0) -> #REF! | G5: =$H$1+RANK('0-1'!G2,data3) -> #REF! | H5: =VLOOKUP(G:G,词库!$A:$C,2,0) -> #REF! | I5: =VLOOKUP(G:G,词库!$A:$C,3,0) -> #REF!
B6: =$C$1+RANK('0-1'!E3,data2) -> #REF! | C6: =VLOOKUP(B:B,词库!$A:$C,2,0) -> #REF! | D6: =VLOOKUP(B:B,词库!$A:$C,3,0) -> #REF! | G6: =$H$1+RANK('0-1'!G3,data3) -> #REF! | H6: =VLOOKUP(G:G,词库!$A:$C,2,0) -> #REF! | I6: =VLOOKUP(G:G,词库!$A:$C,3,0) -> #REF!
B7: =$C$1+RANK('0-1'!E4,data2) -> #REF! | C7: =VLOOKUP(B:B,词库!$A:$C,2,0) -> #REF! | D7: =VLOOKUP(B:B,词库!$A:$C,3,0) -> #REF! | G7: =$H$1+RANK('0-1'!G4,data3) -> #REF! | H7: =VLOOKUP(G:G,词库!$A:$C,2,0) -> #REF! | I7: =VLOOKUP(G:G,词库!$A:$C,3,0) -> #REF!
B8: =$C$1+RANK('0-1'!E5,data2) -> #REF! | C8: =VLOOKUP(B:B,词库!$A:$C,2,0) -> #REF! | D8: =VLOOKUP(B:B,词库!$A:$C,3,0) -> #REF! | G8: =$H$1+RANK('0-1'!G5,data3) -> #REF! | H8: =VLOOKUP(G:G,词库!$A:$C,2,0) -> #REF! | I8: =VLOOKUP(G:G,词库!$A:$C,3,0) -> #REF!
B9: =$C$1+RANK('0-1'!E6,data2) -> #REF! | C9: =VLOOKUP(B:B,词库!$A:$C,2,0) -> #REF! | D9: =VLOOKUP(B:B,词库!$A:$C,3,0) -> #REF! | G9: =$H$1+RANK('0-1'!G6,data3) -> #REF! | H9: =VLOOKUP(G:G,词库!$A:$C,2,0) -> #REF! | I9: =VLOOKUP(G:G,词库!$A:$C,3,0) -> #REF!
B10: =$C$1+RANK('0-1'!E7,data2) -> #REF! | C10: =VLOOKUP(B:B,词库!$A:$C,2,0) -> #REF! | D10: =VLOOKUP(B:B,词库!$A:$C,3,0) -> #REF! | G10: =$H$1+RANK('0-1'!G7,data3) -> #REF! | H10: =VLOOKUP(G:G,词库!$A:$C,2,0) -> #REF! | I10: =VLOOKUP(G:G,词库!$A:$C,3,0) -> #REF!
B11: =$C$1+RANK('0-1'!E8,data2) -> #REF! | C11: =VLOOKUP(B:B,词库!$A:$C,2,0) -> #REF! | D11: =VLOOKUP(B:B,词库!$A:$C,3,0) -> #REF! | G11: =$H$1+RANK('0-1'!G8,data3) -> #REF! | H11: =VLOOKUP(G:G,词库!$A:$C,2,0) -> #REF! | I11: =VLOOKUP(G:G,词库!$A:$C,3,0) -> #REF!
B12: =$C$1+RANK('0-1'!E9,data2) -> #REF! | C12: =VLOOKUP(B:B,词库!$A:$C,2,0) -> #REF! | D12: =VLOOKUP(B:B,词库!$A:$C,3,0) -> #REF! | G12: =$H$1+RANK('0-1'!G9,data3) -> #REF! | H12: =VLOOKUP(G:G,词库!$A:$C,2,0) -> #REF! | I12: =VLOOKUP(G:G,词库!$A:$C,3,0) -> #REF!
B13: =$C$1+RANK('0-1'!E10,data2) -> #REF! | C13: =VLOOKUP(B:B,词库!$A:$C,2,0) -> #REF! | D13: =VLOOKUP(B:B,词库!$A:$C,3,0) -> #REF! | G13: =$H$1+RANK('0-1'!G10,data3) -> #REF! | H13: =VLOOKUP(G:G,词库!$A:$C,2,0) -> #REF! | I13: =VLOOKUP(G:G,词库!$A:$C,3,0) -> #REF!
B14: =$C$1+RANK('0-1'!E11,data2) -> #REF! | C14: =VLOOKUP(B:B,词库!$A:$C,2,0) -> #REF! | D14: =VLOOKUP(B:B,词库!$A:$C,3,0) -> #REF! | G14: =$H$1+RANK('0-1'!G11,data3) -> #REF! | H14: =VLOOKUP(G:G,词库!$A:$C,2,0) -> #REF! | I14: =VLOOKUP(G:G,词库!$A:$C,3,0) -> #REF!
B15: =$C$1+RANK('0-1'!E12,data2) -> #REF! | C15: =VLOOKUP(B:B,词库!$A:$C,2,0) -> #REF! | D15: =VLOOKUP(B:B,词库!$A:$C,3,0) -> #REF! | G15: =$H$1+RANK('0-1'!G12,data3) -> #REF! | H15: =VLOOKUP(G:G,词库!$A:$C,2,0) -> #REF! | I15: =VLOOKUP(G:G,词库!$A:$C,3,0) -> #REF!
... B73: =$C$1+RANK('0-1'!E70,data2) -> #REF! | C73: =VLOOKUP(B:B,词库!$A:$C,2,0) -> #REF! | D73: =VLOOKUP(B:B,词库!$A:$C,3,0) -> #REF! | G73: =$H$1+RANK('0-1'!G70,data3) -> #REF! | H73: =VLOOKUP(G:G,词库!$A:$C,2,0) -> #REF! | I73: =VLOOKUP(G:G,词库!$A:$C,3,0) -> #REF!

Sheet 0-1
A1: =RAND() -> 0.7795754 | C1: =RAND() -> 0.28285853 | E1: =RAND() -> 0.78544592 | G1: =RAND() -> 0.46570174
A2: =RAND() -> 0.58275527 | C2: =RAND() -> 0.71323262 | E2: =RAND() -> 0.72378427 | G2: =RAND() -> 0.45523192
A3: =RAND() -> 0.6175415 | C3: =RAND() -> 0.016392752 | E3: =RAND() -> 0.29565392 | G3: =RAND() -> 0.87038444
A4: =RAND() -> 0.19012002 | C4: =RAND() -> 0.081591173 | E4: =RAND() -> 0.225516 | G4: =RAND() -> 0.91046396
A5: =RAND() -> 0.096775587 | C5: =RAND() -> 0.027891693 | E5: =RAND() -> 0.24192146 | G5: =RAND() -> 0.5988735
A6: =RAND() -> 0.41863185 | C6: =RAND() -> 0.38758134 | E6: =RAND() -> 0.7233733 | G6: =RAND() -> 0.8571804
A7: =RAND() -> 0.48649285 | C7: =RAND() -> 0.68333804 | E7: =RAND() -> 0.99786699 | G7: =RAND() -> 0.55524763
A8: =RAND() -> 0.78399094 | C8: =RAND() -> 0.93246436 | E8: =RAND() -> 0.28514065 | G8: =RAND() -> 0.25116873
A9: =RAND() -> 0.088775133 | C9: =RAND() -> 0.25925391 | E9: =RAND() -> 0.69947331 | G9: =RAND() -> 0.67486822
A10: =RAND() -> 0.29713211 | C10: =RAND() -> 0.35745815 | E10: =RAND() -> 0.77117063 | G10: =RAND() -> 0.3361637
A11: =RAND() -> 0.14312794 | C11: =RAND() -> 0.035106708 | E11: =RAND() -> 0.3390155 | G11: =RAND() -> 0.073474513
A12: =RAND() -> 0.98124895 | C12: =RAND() -> 0.69496669 | E12: =RAND() -> 0.8469158 | G12: =RAND() -> 0.25313608
... A5000: =RAND() -> 0.74104091 | C5000: =RAND() -> 0.44326236 | E5000: =RAND() -> 0.3425189 | G5000: =RAND() -> 0.18028698

Sheet 词库
A1: 序号 | B1: 英文 | C1: 中文释义
A2: 1 | B2: irrational | C2: 不理性的
A3: 2 | B3: omnipresent | C3: 无所不在的，普遍存在的
A4: 3 | B4: formulaic | C4: 俗套的，老套的
A5: 4 | B5: displace | C5: 替代，取代
A6: 5 | B6: unattainable | C6: 达不到的，不可获得的
A7: 6 | B7: topple | C7: 推翻，颠覆
A8: 7 | B8: accessible | C8: 可以理解的，易懂的
A9: 8 | B9: instrumental | C9: 有帮助的，有助于……的
A10: 9 | B10: misguided | C10: 由错误的判断所导致的，不明智的
A11: 10 | B11: evasive | C11: 搪塞的，推诿的，含糊其辞的，逃跑的，躲避的
A12: 11 | B12: intuitive | C12: 凭直觉的，本能的
A13: 12 | B13: counterintuitive | C13: 违反直觉的，不合常理的
... A2676: 2675 | B2676: affiliation | C2676: 联系，从属关系
